marketplace_hpc/__init__.py
marketplace_hpc/version.py
hpc_sdk-0.2.1.dist-info/LICENSE
hpc_sdk-0.2.1.dist-info/METADATA
hpc_sdk-0.2.1.dist-info/WHEEL
hpc_sdk-0.2.1.dist-info/top_level.txt
hpc_sdk-0.2.1.dist-info/RECORD
