Metadata-Version: 2.1
Name: hpc-sdk
Version: 0.2.1
Summary: Software Development Toolkit to communicate with the Materials MarketPlace HPC app.
Home-page: https://github.com/unkcpz/hpc-sdk
Author: Jusong Yu
Author-email: jusong.yu@epfl.ch
License: MIT
Classifier: Development Status :: 2 - Pre-Alpha
Classifier: License :: OSI Approved :: MIT License
Classifier: Programming Language :: Python :: 3
Classifier: Programming Language :: Python :: 3 :: Only
Classifier: Programming Language :: Python :: 3.8
Classifier: Programming Language :: Python :: 3.9
Classifier: Programming Language :: Python :: 3.10
Classifier: Programming Language :: Python :: Implementation :: CPython
Requires-Python: >=3.8
License-File: LICENSE
Requires-Dist: marketplace-sdk (~=0.1.1)
Requires-Dist: requests (~=2.26.0)
Provides-Extra: dev
Requires-Dist: bumpver (==2021.1114) ; extra == 'dev'
Requires-Dist: dunamai (==1.7.0) ; extra == 'dev'
Provides-Extra: pre_commit
Requires-Dist: pre-commit (==2.15.0) ; extra == 'pre_commit'
Provides-Extra: tests
Requires-Dist: pytest (==6.2.5) ; extra == 'tests'
